nb_ui/__init__.py
nb_ui/utils.py
nb_ui/components/__init__.py
nb_ui/components/alerts.py
nb_ui/components/base.py
nb_ui/components/cards.py
nb_ui/components/code.py
nb_ui/components/containers.py
nb_ui/components/headers.py
nb_ui/components/typography.py
nb_ui/theme/__init__.py
nb_ui/theme/antd.py
nb_ui/theme/core.py
nb_ui/theme/dark.py
nb_ui/theme/material.py
nb_ui/theme/provider.py
nb_ui-1.0.0.dist-info/licenses/LICENSE
nb_ui-1.0.0.dist-info/METADATA
nb_ui-1.0.0.dist-info/WHEEL
nb_ui-1.0.0.dist-info/top_level.txt
nb_ui-1.0.0.dist-info/RECORD
