Metadata-Version: 2.4
Name: nb-ui
Version: 1.0.0
Summary: Beautiful web-style components for Jupyter notebooks
Author-email: jeremy vendarwan <noreply@github.com>
License: MIT
Project-URL: Homepage, https://github.com/jvendarwan/nb-ui
Project-URL: Documentation, https://github.com/jvendarwan/nb-ui#readme
Project-URL: Repository, https://github.com/jvendarwan/nb-ui.git
Project-URL: Bug Tracker, https://github.com/jvendarwan/nb-ui/issues
Keywords: jupyter,notebook,ui,components
Classifier: Intended Audience :: Developers
Classifier: Intended Audience :: Science/Research
Classifier: License :: OSI Approved :: MIT License
Classifier: Operating System :: OS Independent
Classifier: Programming Language :: Python :: 3
Classifier: Programming Language :: Python :: 3.12
Classifier: Programming Language :: Python :: 3.11
Classifier: Programming Language :: Python :: 3.10
Classifier: Programming Language :: Python :: 3.9
Classifier: Topic :: Software Development :: Libraries :: Python Modules
Classifier: Topic :: Scientific/Engineering
Requires-Python: >=3.9
License-File: LICENSE
Requires-Dist: ipython>=7.0.0
Provides-Extra: dev
Requires-Dist: pytest>=6.0; extra == "dev"
Requires-Dist: black; extra == "dev"
Requires-Dist: flake8; extra == "dev"
Requires-Dist: twine; extra == "dev"
Requires-Dist: build; extra == "dev"
Dynamic: license-file
